setup.py
pasture/__init__.py
pasture/auth.py
pasture/names.py
pasture/routes.py
pasture/sanitize.py
pasture.egg-info/PKG-INFO
pasture.egg-info/SOURCES.txt
pasture.egg-info/dependency_links.txt
pasture.egg-info/requires.txt
pasture.egg-info/top_level.txt