Metadata-Version: 1.0
Name: pasture
Version: 0.1.0
Summary: a centralized python scripting environment
Home-page: https://github.com/ftzeng/pasture
Author: Francis Tseng
Author-email: f@frnsys.com
License: GPLv3
Platform: UNKNOWN
